setup.py
bin/screenshotuploader
screenshotuploader/__init__.py
screenshotuploader.egg-info/PKG-INFO
screenshotuploader.egg-info/SOURCES.txt
screenshotuploader.egg-info/dependency_links.txt
screenshotuploader.egg-info/not-zip-safe
screenshotuploader.egg-info/top_level.txt