Metadata-Version: 1.0
Name: screenshotuploader
Version: 1.1
Summary: Automagically captures the screenshot of the screen , uploads in imgurl , copies the url into clipboard , deletes the created image file from your desktop 
Home-page: https://github.com/yask123/AutoScreenshotUploader
Author: Yask Srivastava
Author-email: yask123@gmail.com
License: MIT
Platform: UNKNOWN
